ibm_ara/__init__.py
ibm_ara/ara.py
ibm_ara-0.2.0.dist-info/METADATA
ibm_ara-0.2.0.dist-info/WHEEL
ibm_ara-0.2.0.dist-info/RECORD
